swagger_stub_api/__init__.py
swagger_stub_api/app.py
swagger_stub_api/command.py
swagger_stub_api/renderers.py
swagger_stub_api/mock/__init__.py
swagger_stub_api/mock/config.py
swagger_stub_api/mock/parser.py
swagger_stub_api/mock/response.py
swagger_stub_api/mock/utils.py
swagger_stub_api-0.1.4.dist-info/DESCRIPTION.rst
swagger_stub_api-0.1.4.dist-info/METADATA
swagger_stub_api-0.1.4.dist-info/RECORD
swagger_stub_api-0.1.4.dist-info/WHEEL
swagger_stub_api-0.1.4.dist-info/entry_points.txt
swagger_stub_api-0.1.4.dist-info/metadata.json
swagger_stub_api-0.1.4.dist-info/top_level.txt
tests/__init__.py
tests/conftest.py
tests/test_app.py
