Metadata-Version: 2.0
Name: swagger-stub-api
Version: 0.1.4
Summary: Swagger Stub API
Home-page: https://github.com/rai200890/swagger-stub-api
Author: Raissa Ferreira
Author-email: rai2000890@gmail.com
License: UNKNOWN
Keywords: swagger mock api
Platform: unix
Platform: linux
Platform: osx
Platform: cygwin
Platform: win32
Classifier: Natural Language :: English
Classifier: Programming Language :: Python :: 3
Requires-Dist: Flask (>=0.11)
Requires-Dist: python-decouple (>=3.1)
Requires-Dist: swagger-parser (>=1.0)
Requires-Dist: Flask-Cors (>=3.0)
Requires-Dist: click (>=6.7)
Requires-Dist: pyaml (>=17.8)
Requires-Dist: requests (>=2.18)
